pluginutils/__init__.py
pluginutils/db.py
martinbndr_modmail_plugin_utils-1.1.4.dist-info/METADATA
martinbndr_modmail_plugin_utils-1.1.4.dist-info/WHEEL
martinbndr_modmail_plugin_utils-1.1.4.dist-info/top_level.txt
martinbndr_modmail_plugin_utils-1.1.4.dist-info/RECORD
