Metadata-Version: 2.4
Name: martinbndr-modmail-plugin-utils
Version: 1.1.4
Summary: A utility package for my modmail plugins
Author: Martin B.
Project-URL: Homepage, https://github.com/martinbndr/kyb3r-modmail-plugins
Classifier: Programming Language :: Python :: 3
Classifier: Operating System :: OS Independent
Requires-Python: >=3.10
